{
  "algorithm-type-name": "BoxSpreadAlgorithm",
  "algorithm-language": "Python",
  "algorithm-location": "Main/box_spread_algorithm.py",
  "job-queue-handler": "QuantConnect.Queues.JobQueue",
  "api-handler": "QuantConnect.Api.Api",
  "data-folder": "data/",
  "results-folder": "results/",
  "cache-folder": "cache/",
  "brokerage": {
    "brokerage-type": "InteractiveBrokers",
    "interactive-brokers": {
      "host": "127.0.0.1",
      "port": 7497,
      "account": "DU123456",
      "username": "",
      "password": "",
      "trading-mode": "paper"
    }
  },
  "data-queue-handler": "QuantConnect.Lean.Engine.DataFeeds.BrokerageDataQueueHandler",
  "data-aggregator": "QuantConnect.Lean.Engine.DataFeeds.AggregationManager",
  "algorithm-parameters": {
    "config_path": "config/lean_strategy_config.json"
  },
  "notes": {
    "brokerage": "Can be 'InteractiveBrokers' or 'Alpaca'",
    "interactive-brokers": {
      "port": "7497 (paper), 7496 (live) for TWS | 4002 (paper), 4001 (live) for IB Gateway",
      "account": "DU123456 (paper), U123456 (live)"
    },
    "alpaca": {
      "base-url": "https://paper-api.alpaca.markets (paper) | https://api.alpaca.markets (live)",
      "key-id": "PK... (paper) | AK... (live)"
    }
  }
}
